{
"type": "FeatureCollection",
"name": "sample_points",
"crs": { "type": "name", "properties": { "name": "urn:ogc:def:crs:OGC:1.3:CRS84" } },
"features": [
{ "type": "Feature", "properties": { "point_id": 1, "type": "test", "elevation": 368 }, "geometry": { "type": "Point", "coordinates": [ -111.678588428422358, 33.128887849334298 ] } },
{ "type": "Feature", "properties": { "point_id": 2, "type": "test", "elevation": 381 }, "geometry": { "type": "Point", "coordinates": [ -112.009345389185313, 33.501279646997546 ] } },
{ "type": "Feature", "properties": { "point_id": 3, "type": "test", "elevation": 367 }, "geometry": { "type": "Point", "coordinates": [ -111.556001424037177, 33.643621187515087 ] } },
{ "type": "Feature", "properties": { "point_id": 4, "type": "training", "elevation": 420 }, "geometry": { "type": "Point", "coordinates": [ -112.416306299510794, 33.182023111027043 ] } },
{ "type": "Feature", "properties": { "point_id": 5, "type": "validation", "elevation": 429 }, "geometry": { "type": "Point", "coordinates": [ -112.423301520893219, 33.353893383794045 ] } },
{ "type": "Feature", "properties": { "point_id": 6, "type": "test", "elevation": 466 }, "geometry": { "type": "Point", "coordinates": [ -112.03001068279211, 33.165507994754257 ] } },
{ "type": "Feature", "properties": { "point_id": 7, "type": "validation", "elevation": 351 }, "geometry": { "type": "Point", "coordinates": [ -111.673850006580196, 33.060225244224085 ] } },
{ "type": "Feature", "properties": { "point_id": 8, "type": "validation", "elevation": 481 }, "geometry": { "type": "Point", "coordinates": [ -111.799594468423322, 33.658309151507346 ] } },
{ "type": "Feature", "properties": { "point_id": 9, "type": "validation", "elevation": 315 }, "geometry": { "type": "Point", "coordinates": [ -111.891987576171147, 33.47656794759731 ] } },
{ "type": "Feature", "properties": { "point_id": 10, "type": "training", "elevation": 483 }, "geometry": { "type": "Point", "coordinates": [ -111.784946106045922, 33.290042954180038 ] } },
{ "type": "Feature", "properties": { "point_id": 11, "type": "validation", "elevation": 598 }, "geometry": { "type": "Point", "coordinates": [ -112.06330642733549, 33.515501164072347 ] } },
{ "type": "Feature", "properties": { "point_id": 12, "type": "validation", "elevation": 359 }, "geometry": { "type": "Point", "coordinates": [ -111.923357759111099, 33.96511123857988 ] } },
{ "type": "Feature", "properties": { "point_id": 13, "type": "training", "elevation": 583 }, "geometry": { "type": "Point", "coordinates": [ -111.952660674955325, 33.332181500897619 ] } },
{ "type": "Feature", "properties": { "point_id": 14, "type": "test", "elevation": 418 }, "geometry": { "type": "Point", "coordinates": [ -111.599757570055232, 33.906246593289595 ] } },
{ "type": "Feature", "properties": { "point_id": 15, "type": "training", "elevation": 481 }, "geometry": { "type": "Point", "coordinates": [ -112.017377056508749, 33.518499599188424 ] } },
{ "type": "Feature", "properties": { "point_id": 16, "type": "training", "elevation": 593 }, "geometry": { "type": "Point", "coordinates": [ -112.344027855010637, 33.416489146494534 ] } },
{ "type": "Feature", "properties": { "point_id": 17, "type": "validation", "elevation": 436 }, "geometry": { "type": "Point", "coordinates": [ -111.835124115769645, 33.577992311058608 ] } },
{ "type": "Feature", "properties": { "point_id": 18, "type": "training", "elevation": 461 }, "geometry": { "type": "Point", "coordinates": [ -111.920137454052735, 33.729765944102951 ] } },
{ "type": "Feature", "properties": { "point_id": 19, "type": "validation", "elevation": 477 }, "geometry": { "type": "Point", "coordinates": [ -111.696385621353855, 33.890077496550973 ] } },
{ "type": "Feature", "properties": { "point_id": 20, "type": "training", "elevation": 459 }, "geometry": { "type": "Point", "coordinates": [ -112.134618966255545, 33.657149682466333 ] } }
]
}
